assets/logo.svg
assets/pandas_variants.png
assets/variants.png
pydbsp/__init__.py
pydbsp/algorithms/__init__.py
pydbsp/algorithms/datalog.py
pydbsp/algorithms/graph_reachability.py
pydbsp/algorithms/rdfs.py
pydbsp/algorithms/scc.py
pydbsp/core.py
pydbsp/indexed_zset/__init__.py
pydbsp/indexed_zset/functions/bilinear.py
pydbsp/indexed_zset/functions/linear.py
pydbsp/indexed_zset/operators/bilinear.py
pydbsp/indexed_zset/operators/linear.py
pydbsp/lazy_zset/__init__.py
pydbsp/lazy_zset/functions/bilinear.py
pydbsp/lazy_zset/functions/binary.py
pydbsp/lazy_zset/functions/linear.py
pydbsp/lazy_zset/operators/bilinear.py
pydbsp/lazy_zset/operators/binary.py
pydbsp/lazy_zset/operators/linear.py
pydbsp/lazy_zset/operators/unary.py
pydbsp/stream/__init__.py
pydbsp/stream/functions/__init__.py
pydbsp/stream/functions/linear.py
pydbsp/stream/operators/__init__.py
pydbsp/stream/operators/bilinear.py
pydbsp/stream/operators/linear.py
pydbsp/zset/__init__.py
pydbsp/zset/functions/__init__.py
pydbsp/zset/functions/bilinear.py
pydbsp/zset/functions/binary.py
pydbsp/zset/functions/linear.py
pydbsp/zset/operators/__init__.py
pydbsp/zset/operators/bilinear.py
pydbsp/zset/operators/binary.py
pydbsp/zset/operators/linear.py
pydbsp/zset/operators/unary.py
pydbsp-0.6.0.dist-info/METADATA
pydbsp-0.6.0.dist-info/WHEEL
pydbsp-0.6.0.dist-info/RECORD
