Metadata-Version: 2.1
Name: pydbsp
Version: 0.6.0
Summary: A pure-python implementation of the database signal processing theory stream processing paradigm
License: MIT
Author: brurucy
Author-email: brurucy@gmail.com
Requires-Python: >=3.12,<4.0
Classifier: License :: OSI Approved :: MIT License
Classifier: Programming Language :: Python :: 3
Classifier: Programming Language :: Python :: 3.12
